score/slang/__init__.py
score/slang/_common.py
score/slang/_def.py
score/slang/_doc.py
score/slang/_lexer.py
score/slang/_parser.py
score/slang/_renderer.py
score/slang/parsetab.py
score.slang-0.3.2.dist-info/DESCRIPTION.rst
score.slang-0.3.2.dist-info/METADATA
score.slang-0.3.2.dist-info/RECORD
score.slang-0.3.2.dist-info/WHEEL
score.slang-0.3.2.dist-info/metadata.json
score.slang-0.3.2.dist-info/top_level.txt
